{"nodes": [{"id": "c_users_joyda_zcodeproject_nainoforge_packages_student_ai_src_engine_ts", "label": "engine.ts", "file_type": "code", "source_file": "C:\\Users\\joyda\\ZCodeProject\\NainoForge\\packages\\student-ai\\src\\engine.ts", "source_location": "L1"}, {"id": "engine_relationalstateengine", "label": "RelationalStateEngine", "file_type": "code", "source_file": "C:\\Users\\joyda\\ZCodeProject\\NainoForge\\packages\\student-ai\\src\\engine.ts", "source_location": "L26"}, {"id": "engine_relationalstateengine_key", "label": ".key()", "file_type": "code", "source_file": "C:\\Users\\joyda\\ZCodeProject\\NainoForge\\packages\\student-ai\\src\\engine.ts", "source_location": "L29"}, {"id": "engine_relationalstateengine_upsert", "label": ".upsert()", "file_type": "code", "source_file": "C:\\Users\\joyda\\ZCodeProject\\NainoForge\\packages\\student-ai\\src\\engine.ts", "source_location": "L33"}, {"id": "engine_relationalstateengine_getmastery", "label": ".getMastery()", "file_type": "code", "source_file": "C:\\Users\\joyda\\ZCodeProject\\NainoForge\\packages\\student-ai\\src\\engine.ts", "source_location": "L37"}, {"id": "engine_relationalstateengine_decayall", "label": ".decayAll()", "file_type": "code", "source_file": "C:\\Users\\joyda\\ZCodeProject\\NainoForge\\packages\\student-ai\\src\\engine.ts", "source_location": "L42"}, {"id": "engine_turninterruptionengine", "label": "TurnInterruptionEngine", "file_type": "code", "source_file": "C:\\Users\\joyda\\ZCodeProject\\NainoForge\\packages\\student-ai\\src\\engine.ts", "source_location": "L52"}, {"id": "engine_turninterruptionengine_evaluate", "label": ".evaluate()", "file_type": "code", "source_file": "C:\\Users\\joyda\\ZCodeProject\\NainoForge\\packages\\student-ai\\src\\engine.ts", "source_location": "L53"}, {"id": "engine_learnerevidencepack", "label": "LearnerEvidencePack", "file_type": "code", "source_file": "C:\\Users\\joyda\\ZCodeProject\\NainoForge\\packages\\student-ai\\src\\engine.ts", "source_location": "L66"}, {"id": "engine_learnerevidencepack_collect", "label": ".collect()", "file_type": "code", "source_file": "C:\\Users\\joyda\\ZCodeProject\\NainoForge\\packages\\student-ai\\src\\engine.ts", "source_location": "L67"}, {"id": "engine_learnerevidencepack_summary", "label": ".summary()", "file_type": "code", "source_file": "C:\\Users\\joyda\\ZCodeProject\\NainoForge\\packages\\student-ai\\src\\engine.ts", "source_location": "L79"}, {"id": "engine_assessmentengine", "label": "AssessmentEngine", "file_type": "code", "source_file": "C:\\Users\\joyda\\ZCodeProject\\NainoForge\\packages\\student-ai\\src\\engine.ts", "source_location": "L88"}, {"id": "engine_assessmentengine_generate", "label": ".generate()", "file_type": "code", "source_file": "C:\\Users\\joyda\\ZCodeProject\\NainoForge\\packages\\student-ai\\src\\engine.ts", "source_location": "L89"}, {"id": "engine_assessmentengine_grade", "label": ".grade()", "file_type": "code", "source_file": "C:\\Users\\joyda\\ZCodeProject\\NainoForge\\packages\\student-ai\\src\\engine.ts", "source_location": "L109"}, {"id": "engine_sessionarcengine", "label": "SessionArcEngine", "file_type": "code", "source_file": "C:\\Users\\joyda\\ZCodeProject\\NainoForge\\packages\\student-ai\\src\\engine.ts", "source_location": "L117"}, {"id": "engine_sessionarcengine_start", "label": ".start()", "file_type": "code", "source_file": "C:\\Users\\joyda\\ZCodeProject\\NainoForge\\packages\\student-ai\\src\\engine.ts", "source_location": "L118"}, {"id": "engine_sessionarcengine_advance", "label": ".advance()", "file_type": "code", "source_file": "C:\\Users\\joyda\\ZCodeProject\\NainoForge\\packages\\student-ai\\src\\engine.ts", "source_location": "L127"}, {"id": "engine_sessionarcengine_complete", "label": ".complete()", "file_type": "code", "source_file": "C:\\Users\\joyda\\ZCodeProject\\NainoForge\\packages\\student-ai\\src\\engine.ts", "source_location": "L137"}, {"id": "engine_anticopymoat", "label": "AntiCopyMoat", "file_type": "code", "source_file": "C:\\Users\\joyda\\ZCodeProject\\NainoForge\\packages\\student-ai\\src\\engine.ts", "source_location": "L144"}, {"id": "engine_anticopymoat_sid", "label": ".sid()", "file_type": "code", "source_file": "C:\\Users\\joyda\\ZCodeProject\\NainoForge\\packages\\student-ai\\src\\engine.ts", "source_location": "L147"}, {"id": "engine_anticopymoat_record", "label": ".record()", "file_type": "code", "source_file": "C:\\Users\\joyda\\ZCodeProject\\NainoForge\\packages\\student-ai\\src\\engine.ts", "source_location": "L151"}, {"id": "engine_anticopymoat_evaluate", "label": ".evaluate()", "file_type": "code", "source_file": "C:\\Users\\joyda\\ZCodeProject\\NainoForge\\packages\\student-ai\\src\\engine.ts", "source_location": "L157"}], "edges": [{"source": "c_users_joyda_zcodeproject_nainoforge_packages_student_ai_src_engine_ts", "target": "c_users_joyda_zcodeproject_nainoforge_packages_student_ai_src_contracts_ts", "relation": "imports_from", "confidence": "EXTRACTED", "source_file": "C:\\Users\\joyda\\ZCodeProject\\NainoForge\\packages\\student-ai\\src\\engine.ts", "source_location": "L4", "weight": 1.0}, {"source": "c_users_joyda_zcodeproject_nainoforge_packages_student_ai_src_engine_ts", "target": "domain_js", "relation": "imports_from", "confidence": "EXTRACTED", "source_file": "C:\\Users\\joyda\\ZCodeProject\\NainoForge\\packages\\student-ai\\src\\engine.ts", "source_location": "L21", "weight": 1.0}, {"source": "c_users_joyda_zcodeproject_nainoforge_packages_student_ai_src_engine_ts", "target": "domain_js", "relation": "imports_from", "confidence": "EXTRACTED", "source_file": "C:\\Users\\joyda\\ZCodeProject\\NainoForge\\packages\\student-ai\\src\\engine.ts", "source_location": "L22", "weight": 1.0}, {"source": "c_users_joyda_zcodeproject_nainoforge_packages_student_ai_src_engine_ts", "target": "engine_relationalstateengine", "relation": "contains", "confidence": "EXTRACTED", "source_file": "C:\\Users\\joyda\\ZCodeProject\\NainoForge\\packages\\student-ai\\src\\engine.ts", "source_location": "L26", "weight": 1.0}, {"source": "engine_relationalstateengine", "target": "engine_relationalstateengine_key", "relation": "method", "confidence": "EXTRACTED", "source_file": "C:\\Users\\joyda\\ZCodeProject\\NainoForge\\packages\\student-ai\\src\\engine.ts", "source_location": "L29", "weight": 1.0}, {"source": "engine_relationalstateengine", "target": "engine_relationalstateengine_upsert", "relation": "method", "confidence": "EXTRACTED", "source_file": "C:\\Users\\joyda\\ZCodeProject\\NainoForge\\packages\\student-ai\\src\\engine.ts", "source_location": "L33", "weight": 1.0}, {"source": "engine_relationalstateengine", "target": "engine_relationalstateengine_getmastery", "relation": "method", "confidence": "EXTRACTED", "source_file": "C:\\Users\\joyda\\ZCodeProject\\NainoForge\\packages\\student-ai\\src\\engine.ts", "source_location": "L37", "weight": 1.0}, {"source": "engine_relationalstateengine", "target": "engine_relationalstateengine_decayall", "relation": "method", "confidence": "EXTRACTED", "source_file": "C:\\Users\\joyda\\ZCodeProject\\NainoForge\\packages\\student-ai\\src\\engine.ts", "source_location": "L42", "weight": 1.0}, {"source": "c_users_joyda_zcodeproject_nainoforge_packages_student_ai_src_engine_ts", "target": "engine_turninterruptionengine", "relation": "contains", "confidence": "EXTRACTED", "source_file": "C:\\Users\\joyda\\ZCodeProject\\NainoForge\\packages\\student-ai\\src\\engine.ts", "source_location": "L52", "weight": 1.0}, {"source": "engine_turninterruptionengine", "target": "engine_turninterruptionengine_evaluate", "relation": "method", "confidence": "EXTRACTED", "source_file": "C:\\Users\\joyda\\ZCodeProject\\NainoForge\\packages\\student-ai\\src\\engine.ts", "source_location": "L53", "weight": 1.0}, {"source": "c_users_joyda_zcodeproject_nainoforge_packages_student_ai_src_engine_ts", "target": "engine_learnerevidencepack", "relation": "contains", "confidence": "EXTRACTED", "source_file": "C:\\Users\\joyda\\ZCodeProject\\NainoForge\\packages\\student-ai\\src\\engine.ts", "source_location": "L66", "weight": 1.0}, {"source": "engine_learnerevidencepack", "target": "engine_learnerevidencepack_collect", "relation": "method", "confidence": "EXTRACTED", "source_file": "C:\\Users\\joyda\\ZCodeProject\\NainoForge\\packages\\student-ai\\src\\engine.ts", "source_location": "L67", "weight": 1.0}, {"source": "engine_learnerevidencepack", "target": "engine_learnerevidencepack_summary", "relation": "method", "confidence": "EXTRACTED", "source_file": "C:\\Users\\joyda\\ZCodeProject\\NainoForge\\packages\\student-ai\\src\\engine.ts", "source_location": "L79", "weight": 1.0}, {"source": "c_users_joyda_zcodeproject_nainoforge_packages_student_ai_src_engine_ts", "target": "engine_assessmentengine", "relation": "contains", "confidence": "EXTRACTED", "source_file": "C:\\Users\\joyda\\ZCodeProject\\NainoForge\\packages\\student-ai\\src\\engine.ts", "source_location": "L88", "weight": 1.0}, {"source": "engine_assessmentengine", "target": "engine_assessmentengine_generate", "relation": "method", "confidence": "EXTRACTED", "source_file": "C:\\Users\\joyda\\ZCodeProject\\NainoForge\\packages\\student-ai\\src\\engine.ts", "source_location": "L89", "weight": 1.0}, {"source": "engine_assessmentengine", "target": "engine_assessmentengine_grade", "relation": "method", "confidence": "EXTRACTED", "source_file": "C:\\Users\\joyda\\ZCodeProject\\NainoForge\\packages\\student-ai\\src\\engine.ts", "source_location": "L109", "weight": 1.0}, {"source": "c_users_joyda_zcodeproject_nainoforge_packages_student_ai_src_engine_ts", "target": "engine_sessionarcengine", "relation": "contains", "confidence": "EXTRACTED", "source_file": "C:\\Users\\joyda\\ZCodeProject\\NainoForge\\packages\\student-ai\\src\\engine.ts", "source_location": "L117", "weight": 1.0}, {"source": "engine_sessionarcengine", "target": "engine_sessionarcengine_start", "relation": "method", "confidence": "EXTRACTED", "source_file": "C:\\Users\\joyda\\ZCodeProject\\NainoForge\\packages\\student-ai\\src\\engine.ts", "source_location": "L118", "weight": 1.0}, {"source": "engine_sessionarcengine", "target": "engine_sessionarcengine_advance", "relation": "method", "confidence": "EXTRACTED", "source_file": "C:\\Users\\joyda\\ZCodeProject\\NainoForge\\packages\\student-ai\\src\\engine.ts", "source_location": "L127", "weight": 1.0}, {"source": "engine_sessionarcengine", "target": "engine_sessionarcengine_complete", "relation": "method", "confidence": "EXTRACTED", "source_file": "C:\\Users\\joyda\\ZCodeProject\\NainoForge\\packages\\student-ai\\src\\engine.ts", "source_location": "L137", "weight": 1.0}, {"source": "c_users_joyda_zcodeproject_nainoforge_packages_student_ai_src_engine_ts", "target": "engine_anticopymoat", "relation": "contains", "confidence": "EXTRACTED", "source_file": "C:\\Users\\joyda\\ZCodeProject\\NainoForge\\packages\\student-ai\\src\\engine.ts", "source_location": "L144", "weight": 1.0}, {"source": "engine_anticopymoat", "target": "engine_anticopymoat_sid", "relation": "method", "confidence": "EXTRACTED", "source_file": "C:\\Users\\joyda\\ZCodeProject\\NainoForge\\packages\\student-ai\\src\\engine.ts", "source_location": "L147", "weight": 1.0}, {"source": "engine_anticopymoat", "target": "engine_anticopymoat_record", "relation": "method", "confidence": "EXTRACTED", "source_file": "C:\\Users\\joyda\\ZCodeProject\\NainoForge\\packages\\student-ai\\src\\engine.ts", "source_location": "L151", "weight": 1.0}, {"source": "engine_anticopymoat", "target": "engine_anticopymoat_evaluate", "relation": "method", "confidence": "EXTRACTED", "source_file": "C:\\Users\\joyda\\ZCodeProject\\NainoForge\\packages\\student-ai\\src\\engine.ts", "source_location": "L157", "weight": 1.0}, {"source": "engine_relationalstateengine_upsert", "target": "engine_relationalstateengine_key", "relation": "calls", "confidence": "EXTRACTED", "source_file": "C:\\Users\\joyda\\ZCodeProject\\NainoForge\\packages\\student-ai\\src\\engine.ts", "source_location": "L34", "weight": 1.0}, {"source": "engine_relationalstateengine_getmastery", "target": "engine_relationalstateengine_key", "relation": "calls", "confidence": "EXTRACTED", "source_file": "C:\\Users\\joyda\\ZCodeProject\\NainoForge\\packages\\student-ai\\src\\engine.ts", "source_location": "L38", "weight": 1.0}, {"source": "engine_anticopymoat_record", "target": "engine_anticopymoat_sid", "relation": "calls", "confidence": "EXTRACTED", "source_file": "C:\\Users\\joyda\\ZCodeProject\\NainoForge\\packages\\student-ai\\src\\engine.ts", "source_location": "L152", "weight": 1.0}], "raw_calls": [{"caller_nid": "engine_relationalstateengine_upsert", "callee": "set", "source_file": "C:\\Users\\joyda\\ZCodeProject\\NainoForge\\packages\\student-ai\\src\\engine.ts", "source_location": "L34"}, {"caller_nid": "engine_relationalstateengine_getmastery", "callee": "get", "source_file": "C:\\Users\\joyda\\ZCodeProject\\NainoForge\\packages\\student-ai\\src\\engine.ts", "source_location": "L38"}, {"caller_nid": "engine_relationalstateengine_decayall", "callee": "values", "source_file": "C:\\Users\\joyda\\ZCodeProject\\NainoForge\\packages\\student-ai\\src\\engine.ts", "source_location": "L44"}, {"caller_nid": "engine_relationalstateengine_decayall", "callee": "max", "source_file": "C:\\Users\\joyda\\ZCodeProject\\NainoForge\\packages\\student-ai\\src\\engine.ts", "source_location": "L45"}, {"caller_nid": "engine_turninterruptionengine_evaluate", "callee": "includes", "source_file": "C:\\Users\\joyda\\ZCodeProject\\NainoForge\\packages\\student-ai\\src\\engine.ts", "source_location": "L57"}, {"caller_nid": "engine_learnerevidencepack_collect", "callee": "slice", "source_file": "C:\\Users\\joyda\\ZCodeProject\\NainoForge\\packages\\student-ai\\src\\engine.ts", "source_location": "L68"}, {"caller_nid": "engine_learnerevidencepack_summary", "callee": "slice", "source_file": "C:\\Users\\joyda\\ZCodeProject\\NainoForge\\packages\\student-ai\\src\\engine.ts", "source_location": "L81"}, {"caller_nid": "engine_learnerevidencepack_summary", "callee": "sort", "source_file": "C:\\Users\\joyda\\ZCodeProject\\NainoForge\\packages\\student-ai\\src\\engine.ts", "source_location": "L81"}, {"caller_nid": "engine_learnerevidencepack_summary", "callee": "join", "source_file": "C:\\Users\\joyda\\ZCodeProject\\NainoForge\\packages\\student-ai\\src\\engine.ts", "source_location": "L82"}, {"caller_nid": "engine_learnerevidencepack_summary", "callee": "map", "source_file": "C:\\Users\\joyda\\ZCodeProject\\NainoForge\\packages\\student-ai\\src\\engine.ts", "source_location": "L82"}, {"caller_nid": "engine_assessmentengine_generate", "callee": "randomUUID", "source_file": "C:\\Users\\joyda\\ZCodeProject\\NainoForge\\packages\\student-ai\\src\\engine.ts", "source_location": "L90"}, {"caller_nid": "engine_assessmentengine_generate", "callee": "join", "source_file": "C:\\Users\\joyda\\ZCodeProject\\NainoForge\\packages\\student-ai\\src\\engine.ts", "source_location": "L91"}, {"caller_nid": "engine_assessmentengine_generate", "callee": "slice", "source_file": "C:\\Users\\joyda\\ZCodeProject\\NainoForge\\packages\\student-ai\\src\\engine.ts", "source_location": "L91"}, {"caller_nid": "engine_assessmentengine_generate", "callee": "split", "source_file": "C:\\Users\\joyda\\ZCodeProject\\NainoForge\\packages\\student-ai\\src\\engine.ts", "source_location": "L91"}, {"caller_nid": "engine_assessmentengine_generate", "callee": "slice", "source_file": "C:\\Users\\joyda\\ZCodeProject\\NainoForge\\packages\\student-ai\\src\\engine.ts", "source_location": "L95"}, {"caller_nid": "engine_assessmentengine_generate", "callee": "replace", "source_file": "C:\\Users\\joyda\\ZCodeProject\\NainoForge\\packages\\student-ai\\src\\engine.ts", "source_location": "L101"}, {"caller_nid": "engine_assessmentengine_generate", "callee": "slice", "source_file": "C:\\Users\\joyda\\ZCodeProject\\NainoForge\\packages\\student-ai\\src\\engine.ts", "source_location": "L103"}, {"caller_nid": "engine_assessmentengine_generate", "callee": "slice", "source_file": "C:\\Users\\joyda\\ZCodeProject\\NainoForge\\packages\\student-ai\\src\\engine.ts", "source_location": "L105"}, {"caller_nid": "engine_sessionarcengine_start", "callee": "randomUUID", "source_file": "C:\\Users\\joyda\\ZCodeProject\\NainoForge\\packages\\student-ai\\src\\engine.ts", "source_location": "L120"}, {"caller_nid": "engine_sessionarcengine_start", "callee": "now", "source_file": "C:\\Users\\joyda\\ZCodeProject\\NainoForge\\packages\\student-ai\\src\\engine.ts", "source_location": "L123"}, {"caller_nid": "engine_sessionarcengine_complete", "callee": "now", "source_file": "C:\\Users\\joyda\\ZCodeProject\\NainoForge\\packages\\student-ai\\src\\engine.ts", "source_location": "L138"}, {"caller_nid": "engine_anticopymoat_record", "callee": "get", "source_file": "C:\\Users\\joyda\\ZCodeProject\\NainoForge\\packages\\student-ai\\src\\engine.ts", "source_location": "L152"}, {"caller_nid": "engine_anticopymoat_record", "callee": "push", "source_file": "C:\\Users\\joyda\\ZCodeProject\\NainoForge\\packages\\student-ai\\src\\engine.ts", "source_location": "L153"}, {"caller_nid": "engine_anticopymoat_record", "callee": "set", "source_file": "C:\\Users\\joyda\\ZCodeProject\\NainoForge\\packages\\student-ai\\src\\engine.ts", "source_location": "L154"}, {"caller_nid": "engine_anticopymoat_evaluate", "callee": "max", "source_file": "C:\\Users\\joyda\\ZCodeProject\\NainoForge\\packages\\student-ai\\src\\engine.ts", "source_location": "L159"}, {"caller_nid": "engine_anticopymoat_evaluate", "callee": "min", "source_file": "C:\\Users\\joyda\\ZCodeProject\\NainoForge\\packages\\student-ai\\src\\engine.ts", "source_location": "L159"}]}